Abhay/__init__.py
SpeechToText/__init__.py
deardavil-0.1.dist-info/METADATA
deardavil-0.1.dist-info/WHEEL
deardavil-0.1.dist-info/top_level.txt
deardavil-0.1.dist-info/RECORD
