Metadata-Version: 2.4
Name: DearDavil
Version: 0.1
Requires-Dist: SpeechRecognition
Requires-Dist: pyaudio
Requires-Dist: mtranslate
Requires-Dist: colorama
Dynamic: requires-dist
